src/mem.v
`ifndef __READ_WRITE_MEMORY
`define __READ_WRITE_MEMORY

// 1 word, 4 bytes, 32 bits
module MEM (
    output reg [31:0] out,  // load 32-bit data 
    input [3:0] byte_addr,  // 16 byte_addr options => lg16 = 4 bits 
    input [31:0] data_i,    // 32-bit data to store
    input e_read, e_write
);

    reg [7:0] memory [15:0];

    initial begin
        memory[0] =  8'h0;
        memory[1] =  8'h1;
        memory[2] =  8'h2;
        memory[3] =  8'h3;
        memory[4] =  8'h4;
        memory[5] =  8'h5;
        memory[6] =  8'h6;
        memory[7] =  8'h7;
        memory[8] =  8'h8;
        memory[9] =  8'h9;
        memory[10] = 8'hA;
        memory[11] = 8'hB;
        memory[12] = 8'hC;
        memory[13] = 8'hD;
        memory[14] = 8'hE;
        memory[15] = 8'hF;
    end

    wire [3:0] start_addr;
    assign start_addr = {byte_addr[3:2], 2'b0};

    always@(*) begin
        if (e_write) begin
            memory[start_addr]   =  data_i[31:24];
            memory[start_addr+1] =  data_i[23:16];
            memory[start_addr+2] =  data_i[15:8];
            memory[start_addr+3] =  data_i[7:0];
            out = 32'b0;
        end
        else if (e_read) begin
            out = {
                memory[start_addr], memory[start_addr+1],
                memory[start_addr+2], memory[start_addr+3]
            };
        end
        else begin
            out = 32'b0;
        end
    end
    
endmodule

`endif

test/tb_mem.v
`include "src/mem.v"

module tb;

    wire [31:0] out;  
    reg [3:0] byte_addr;  
    reg [31:0] data_i;    
    reg e_read, e_write;

    MEM DM(out, byte_addr, data_i, e_read, e_write);

    initial begin
        $dumpfile("build/mem.vcd");
        $dumpvars(0, tb);
        e_read = 0; e_write = 0;
        #1 e_read = 1;
        #1 byte_addr = 4'd0; 
        #1 byte_addr = 4'd1; 
        #1 byte_addr = 4'd2; 
        #1 byte_addr = 4'd3; 
        #1 byte_addr = 4'd4; 
        #1 byte_addr = 4'd5; 
        e_write = 1; e_read = 0;
        data_i = 32'h1A2B3C4D;
        #1 byte_addr = 4'd6; 
        e_write = 0; e_read = 1;
        #1 byte_addr = 4'd7; 
        e_write = 0; e_read = 0;
        #1 byte_addr = 4'd8; 
        e_write = 0; e_read = 1;
        #1 byte_addr = 4'd4; 
        #1 byte_addr = 4'd5; 
        #1 byte_addr = 4'd6;
        #1 byte_addr = 4'd7; 
        #1 byte_addr = 4'd13; 
        #1 byte_addr = 4'd14; 
        #1 byte_addr = 4'd15; 
        #5 $finish;
    end

    
endmodule

build/mem.vcd
$date
	Thu Dec 21 01:26:35 2023
$end
$version
	Icarus Verilog
$end
$timescale
	1s
$end
$scope module tb $end
$var wire 32 ! out [31:0] $end
$var reg 4 " byte_addr [3:0] $end
$var reg 32 # data_i [31:0] $end
$var reg 1 $ e_read $end
$var reg 1 % e_write $end
$scope module DM $end
$var wire 4 & byte_addr [3:0] $end
$var wire 32 ' data_i [31:0] $end
$var wire 1 $ e_read $end
$var wire 1 % e_write $end
$var wire 4 ( start_addr [3:0] $end
$var reg 32 ) out [31:0] $end
$upscope $end
$upscope $end
$enddefinitions $end
#0
$dumpvars
b0 )
bx00 (
bx '
bx &
0%
0$
bx #
bx "
b0 !
$end
#1
bx !
bx )
1$
#2
b10000001000000011 !
b10000001000000011 )
b0 (
b0 "
b0 &
#3
b1 "
b1 &
#4
b10 "
b10 &
#5
b11 "
b11 &
#6
b100000001010000011000000111 !
b100000001010000011000000111 )
b100 (
b100 "
b100 &
#7
b0 !
b0 )
b11010001010110011110001001101 #
b11010001010110011110001001101 '
0$
1%
b101 "
b101 &
#8
b11010001010110011110001001101 !
b11010001010110011110001001101 )
1$
0%
b110 "
b110 &
#9
b0 !
b0 )
0$
b111 "
b111 &
#10
b1000000010010000101000001011 !
b1000000010010000101000001011 )
b1000 (
1$
b1000 "
b1000 &
#11
b11010001010110011110001001101 !
b11010001010110011110001001101 )
b100 (
b100 "
b100 &
#12
b101 "
b101 &
#13
b110 "
b110 &
#14
b111 "
b111 &
#15
b1100000011010000111000001111 !
b1100000011010000111000001111 )
b1100 (
b1101 "
b1101 &
#16
b1110 "
b1110 &
#17
b1111 "
b1111 &
